<object-stream>
  <long>1457583856324</long>
  <us.ihmc.humanoidRobotics.communication.packets.walking.FootstepDataListMessage>
    <uniqueId>-1</uniqueId>
    <destination>0</destination>
    <footstepDataList>
      <us.ihmc.humanoidRobotics.communication.packets.walking.FootstepDataMessage>
        <uniqueId>0</uniqueId>
        <destination>0</destination>
        <origin>AT_ANKLE_FRAME</origin>
        <robotSide>RIGHT</robotSide>
        <location>
          <x>0.35801227058437474</x>
          <y>-0.2178839375445521</y>
          <z>.09</z>
        </location>
        <orientation>
          <x>0.0033380751509319547</x>
          <y>0.0060011596128933505</y>
          <z>0.0035528842929810705</z>
          <w>0.9999701097286798</w>
        </orientation>
        <trajectoryType>DEFAULT</trajectoryType>
        <swingHeight>0.0</swingHeight>
      </us.ihmc.humanoidRobotics.communication.packets.walking.FootstepDataMessage>
      <us.ihmc.humanoidRobotics.communication.packets.walking.FootstepDataMessage>
        <uniqueId>0</uniqueId>
        <destination>0</destination>
        <origin>AT_ANKLE_FRAME</origin>
        <robotSide>LEFT</robotSide>
        <location>
          <x>0.7537224724110634</x>
          <y>0.04183302887370008</y>
          <z>.09</z>
        </location>
        <orientation>
          <x>-1.1651165434174243E-4</x>
          <y>0.0015395393915390602</y>
          <z>0.0035742441276513303</z>
          <w>0.9999924204824816</w>
        </orientation>
        <trajectoryType>DEFAULT</trajectoryType>
        <swingHeight>0.0</swingHeight>
      </us.ihmc.humanoidRobotics.communication.packets.walking.FootstepDataMessage>
      <us.ihmc.humanoidRobotics.communication.packets.walking.FootstepDataMessage>
        <uniqueId>0</uniqueId>
        <destination>0</destination>
        <origin>AT_ANKLE_FRAME</origin>
        <robotSide>RIGHT</robotSide>
        <location>
          <x>0.7551818492812659</x>
          <y>-0.20860371484308754</y>
          <z>.09</z>
        </location>
        <orientation>
          <x>0.0025136373658113335</x>
          <y>-4.1334771937638414E-4</y>
          <z>0.003575562449809849</z>
          <w>0.9999903630155761</w>
        </orientation>
        <trajectoryType>DEFAULT</trajectoryType>
        <swingHeight>0.0</swingHeight>
      </us.ihmc.humanoidRobotics.communication.packets.walking.FootstepDataMessage>
    </footstepDataList>
    <swingTime>0.0</swingTime>
    <transferTime>0.0</transferTime>
  </us.ihmc.humanoidRobotics.communication.packets.walking.FootstepDataListMessage>
  <long>1457583856325</long>
  <us.ihmc.humanoidRobotics.communication.packets.walking.PauseWalkingMessage>
    <uniqueId>-1</uniqueId>
    <destination>0</destination>
    <pause>true</pause>
  </us.ihmc.humanoidRobotics.communication.packets.walking.PauseWalkingMessage>
  <long>1457583856325</long>
  <us.ihmc.humanoidRobotics.communication.packets.walking.FootstepDataListMessage>
    <uniqueId>-1</uniqueId>
    <destination>0</destination>
    <footstepDataList>
      <us.ihmc.humanoidRobotics.communication.packets.walking.FootstepDataMessage>
        <uniqueId>0</uniqueId>
        <destination>0</destination>
        <origin>AT_ANKLE_FRAME</origin>
        <robotSide>LEFT</robotSide>
        <location>
          <x>0.8018055756656133</x>
          <y>0.18412055007195574</y>
          <z>.09</z>
        </location>
        <orientation>
          <x>0.025427661638809794</x>
          <y>-0.026269017796840412</y>
          <z>-0.03314048200832464</z>
          <w>0.998781798582567</w>
        </orientation>
        <trajectoryType>DEFAULT</trajectoryType>
        <swingHeight>0.0</swingHeight>
      </us.ihmc.humanoidRobotics.communication.packets.walking.FootstepDataMessage>
      <us.ihmc.humanoidRobotics.communication.packets.walking.FootstepDataMessage>
        <uniqueId>0</uniqueId>
        <destination>0</destination>
        <origin>AT_ANKLE_FRAME</origin>
        <robotSide>RIGHT</robotSide>
        <location>
          <x>0.9179143737221224</x>
          <y>-0.15502340990826224</y>
          <z>.09</z>
        </location>
        <orientation>
          <x>0.002001072509080682</x>
          <y>-0.03457796465628506</y>
          <z>-0.0419426752996716</z>
          <w>0.9985194900740538</w>
        </orientation>
        <trajectoryType>DEFAULT</trajectoryType>
        <swingHeight>0.0</swingHeight>
      </us.ihmc.humanoidRobotics.communication.packets.walking.FootstepDataMessage>
      <us.ihmc.humanoidRobotics.communication.packets.walking.FootstepDataMessage>
        <uniqueId>0</uniqueId>
        <destination>0</destination>
        <origin>AT_ANKLE_FRAME</origin>
        <robotSide>LEFT</robotSide>
        <location>
          <x>1.1055488190227736</x>
          <y>0.07417291540284082</y>
          <z>.12</z>
        </location>
        <orientation>
          <x>0.054249338760572426</x>
          <y>-0.15664097158605744</y>
          <z>-0.03194261322336017</z>
          <w>0.9856471400684321</w>
        </orientation>
        <trajectoryType>DEFAULT</trajectoryType>
        <swingHeight>0.0</swingHeight>
      </us.ihmc.humanoidRobotics.communication.packets.walking.FootstepDataMessage>
      <us.ihmc.humanoidRobotics.communication.packets.walking.FootstepDataMessage>
        <uniqueId>0</uniqueId>
        <destination>0</destination>
        <origin>AT_ANKLE_FRAME</origin>
        <robotSide>RIGHT</robotSide>
        <location>
          <x>1.214410690404198</x>
          <y>-0.17125868661128185</y>
          <z>.145</z>
        </location>
        <orientation>
          <x>-0.012298185810682693</x>
          <y>-0.14433945567362388</y>
          <z>-0.042495059041586854</z>
          <w>0.9885388440110282</w>
        </orientation>
        <trajectoryType>DEFAULT</trajectoryType>
        <swingHeight>0.0</swingHeight>
      </us.ihmc.humanoidRobotics.communication.packets.walking.FootstepDataMessage>
      <us.ihmc.humanoidRobotics.communication.packets.walking.FootstepDataMessage>
        <uniqueId>0</uniqueId>
        <destination>0</destination>
        <origin>AT_ANKLE_FRAME</origin>
        <robotSide>LEFT</robotSide>
        <location>
          <x>1.3957108804515785</x>
          <y>0.061479415391915176</y>
          <z>.2</z>
        </location>
        <orientation>
          <x>0.005451968813995574</x>
          <y>-0.12385807730221088</y>
          <z>-0.040391385614190436</z>
          <w>0.9914625503221071</w>
        </orientation>
        <trajectoryType>DEFAULT</trajectoryType>
        <swingHeight>0.0</swingHeight>
      </us.ihmc.humanoidRobotics.communication.packets.walking.FootstepDataMessage>
      <us.ihmc.humanoidRobotics.communication.packets.walking.FootstepDataMessage>
        <uniqueId>0</uniqueId>
        <destination>0</destination>
        <origin>AT_ANKLE_FRAME</origin>
        <robotSide>RIGHT</robotSide>
        <location>
          <x>1.373947877272907</x>
          <y>-0.18636162383043114</y>
          <z>.21</z>
        </location>
        <orientation>
          <x>-0.0018950853997859723</x>
          <y>-0.12854159942701113</y>
          <z>-0.041234859064142614</z>
          <w>0.9908446660632703</w>
        </orientation>
        <trajectoryType>DEFAULT</trajectoryType>
        <swingHeight>0.0</swingHeight>
      </us.ihmc.humanoidRobotics.communication.packets.walking.FootstepDataMessage>
    </footstepDataList>
    <swingTime>0.0</swingTime>
    <transferTime>0.0</transferTime>
  </us.ihmc.humanoidRobotics.communication.packets.walking.FootstepDataListMessage>
  <long>1457583856326</long>
  <us.ihmc.humanoidRobotics.communication.packets.walking.PauseWalkingMessage>
    <uniqueId>-1</uniqueId>
    <destination>0</destination>
    <pause>true</pause>
  </us.ihmc.humanoidRobotics.communication.packets.walking.PauseWalkingMessage>
  <long>1457583856326</long>
  <us.ihmc.humanoidRobotics.communication.packets.walking.FootstepDataListMessage>
    <uniqueId>-1</uniqueId>
    <destination>0</destination>
    <footstepDataList>
      <us.ihmc.humanoidRobotics.communication.packets.walking.FootstepDataMessage>
        <uniqueId>0</uniqueId>
        <destination>0</destination>
        <origin>AT_ANKLE_FRAME</origin>
        <robotSide>RIGHT</robotSide>
        <location>
          <x>1.399553709893733</x>
          <y>-0.1842173706217436</y>
          <z>.21</z>
        </location>
        <orientation>
          <x>-0.002536873056239694</x>
          <y>-0.1283752583645514</y>
          <z>0.013809198431849606</z>
          <w>0.9916262720166308</w>
        </orientation>
        <trajectoryType>DEFAULT</trajectoryType>
        <swingHeight>0.0</swingHeight>
      </us.ihmc.humanoidRobotics.communication.packets.walking.FootstepDataMessage>
      <us.ihmc.humanoidRobotics.communication.packets.walking.FootstepDataMessage>
        <uniqueId>0</uniqueId>
        <destination>0</destination>
        <origin>AT_ANKLE_FRAME</origin>
        <robotSide>LEFT</robotSide>
        <location>
          <x>1.71158306819223</x>
          <y>0.1970596067193278</y>
          <z>.23</z>
        </location>
        <orientation>
          <x>0.017451017801187206</x>
          <y>0.12049555722275644</y>
          <z>0.04585244712748365</z>
          <w>0.9915007996767836</w>
        </orientation>
        <trajectoryType>DEFAULT</trajectoryType>
        <swingHeight>0.0</swingHeight>
      </us.ihmc.humanoidRobotics.communication.packets.walking.FootstepDataMessage>
      <us.ihmc.humanoidRobotics.communication.packets.walking.FootstepDataMessage>
        <uniqueId>0</uniqueId>
        <destination>0</destination>
        <origin>AT_ANKLE_FRAME</origin>
        <robotSide>RIGHT</robotSide>
        <location>
          <x>1.7664705595259769</x>
          <y>-0.0896101333836647</y>
          <z>.23</z>
        </location>
        <orientation>
          <x>0.012519722504541865</x>
          <y>0.13724016152471977</y>
          <z>0.04591007410758</z>
          <w>0.9893940871606797</w>
        </orientation>
        <trajectoryType>DEFAULT</trajectoryType>
        <swingHeight>0.0</swingHeight>
      </us.ihmc.humanoidRobotics.communication.packets.walking.FootstepDataMessage>
      <us.ihmc.humanoidRobotics.communication.packets.walking.FootstepDataMessage>
        <uniqueId>0</uniqueId>
        <destination>0</destination>
        <origin>AT_ANKLE_FRAME</origin>
        <robotSide>LEFT</robotSide>
        <location>
          <x>1.9151290000881962</x>
          <y>0.17665060118369927</y>
          <z>.18</z>
        </location>
        <orientation>
          <x>0.00977409944370276</x>
          <y>0.14205428088971064</y>
          <z>0.04613860215464631</z>
          <w>0.9887346851669497</w>
        </orientation>
        <trajectoryType>DEFAULT</trajectoryType>
        <swingHeight>0.0</swingHeight>
      </us.ihmc.humanoidRobotics.communication.packets.walking.FootstepDataMessage>
      <us.ihmc.humanoidRobotics.communication.packets.walking.FootstepDataMessage>
        <uniqueId>0</uniqueId>
        <destination>0</destination>
        <origin>AT_ANKLE_FRAME</origin>
        <robotSide>RIGHT</robotSide>
        <location>
          <x>1.9400829487532982</x>
          <y>-0.07132741458293027</y>
          <z>.18</z>
        </location>
        <orientation>
          <x>0.005064921099470477</x>
          <y>0.1453070660929657</y>
          <z>0.046722280630632426</z>
          <w>0.9882698172110606</w>
        </orientation>
        <trajectoryType>DEFAULT</trajectoryType>
        <swingHeight>0.0</swingHeight>
      </us.ihmc.humanoidRobotics.communication.packets.walking.FootstepDataMessage>
    </footstepDataList>
    <swingTime>0.0</swingTime>
    <transferTime>0.0</transferTime>
  </us.ihmc.humanoidRobotics.communication.packets.walking.FootstepDataListMessage>
  <long>1457583856327</long>
  <us.ihmc.humanoidRobotics.communication.packets.walking.PauseWalkingMessage>
    <uniqueId>-1</uniqueId>
    <destination>0</destination>
    <pause>true</pause>
  </us.ihmc.humanoidRobotics.communication.packets.walking.PauseWalkingMessage>
  <long>1457583856327</long>
  <us.ihmc.humanoidRobotics.communication.packets.walking.FootstepDataListMessage>
    <uniqueId>-1</uniqueId>
    <destination>0</destination>
    <footstepDataList>
      <us.ihmc.humanoidRobotics.communication.packets.walking.FootstepDataMessage>
        <uniqueId>0</uniqueId>
        <destination>0</destination>
        <origin>AT_ANKLE_FRAME</origin>
        <robotSide>RIGHT</robotSide>
        <location>
          <x>2.026579553287282</x>
          <y>-0.03255678645951963</y>
          <z>.15</z>
        </location>
        <orientation>
          <x>-0.03996137793337269</x>
          <y>0.16362751490552138</y>
          <z>0.0010410711145800151</z>
          <w>0.9857119461640119</w>
        </orientation>
        <trajectoryType>DEFAULT</trajectoryType>
        <swingHeight>0.0</swingHeight>
      </us.ihmc.humanoidRobotics.communication.packets.walking.FootstepDataMessage>
      <us.ihmc.humanoidRobotics.communication.packets.walking.FootstepDataMessage>
        <uniqueId>0</uniqueId>
        <destination>0</destination>
        <origin>AT_ANKLE_FRAME</origin>
        <robotSide>LEFT</robotSide>
        <location>
          <x>2.310312050794755</x>
          <y>0.2365094687711953</y>
          <z>.09</z>
        </location>
        <orientation>
          <x>0.009031237629051279</x>
          <y>0.00978788936302821</y>
          <z>-0.005867111523041889</z>
          <w>0.9998940998781226</w>
        </orientation>
        <trajectoryType>DEFAULT</trajectoryType>
        <swingHeight>0.0</swingHeight>
      </us.ihmc.humanoidRobotics.communication.packets.walking.FootstepDataMessage>
      <us.ihmc.humanoidRobotics.communication.packets.walking.FootstepDataMessage>
        <uniqueId>0</uniqueId>
        <destination>0</destination>
        <origin>AT_ANKLE_FRAME</origin>
        <robotSide>RIGHT</robotSide>
        <location>
          <x>2.3331231004116058</x>
          <y>0.0018309716994655556</y>
          <z>.09</z>
        </location>
        <orientation>
          <x>-0.005798159674052659</x>
          <y>-0.0012900691047702047</y>
          <z>-0.005783730336863959</z>
          <w>0.9999656321741711</w>
        </orientation>
        <trajectoryType>DEFAULT</trajectoryType>
        <swingHeight>0.0</swingHeight>
      </us.ihmc.humanoidRobotics.communication.packets.walking.FootstepDataMessage>
      <us.ihmc.humanoidRobotics.communication.packets.walking.FootstepDataMessage>
        <uniqueId>0</uniqueId>
        <destination>0</destination>
        <origin>AT_ANKLE_FRAME</origin>
        <robotSide>LEFT</robotSide>
        <location>
          <x>2.5046825764162355</x>
          <y>0.24812645454328738</y>
          <z>.09</z>
        </location>
        <orientation>
          <x>0.004613736234819086</x>
          <y>0.010144442876422046</y>
          <z>-0.005825354247955351</z>
          <w>0.999920931356359</w>
        </orientation>
        <trajectoryType>DEFAULT</trajectoryType>
        <swingHeight>0.0</swingHeight>
      </us.ihmc.humanoidRobotics.communication.packets.walking.FootstepDataMessage>
      <us.ihmc.humanoidRobotics.communication.packets.walking.FootstepDataMessage>
        <uniqueId>0</uniqueId>
        <destination>0</destination>
        <origin>AT_ANKLE_FRAME</origin>
        <robotSide>RIGHT</robotSide>
        <location>
          <x>2.5018089388913167</x>
          <y>-0.0011667484879833295</y>
          <z>.09</z>
        </location>
        <orientation>
          <x>5.09622949998805E-4</x>
          <y>0.010161212697416818</y>
          <z>-0.00578366401508213</z>
          <w>0.999931517290823</w>
        </orientation>
        <trajectoryType>DEFAULT</trajectoryType>
        <swingHeight>0.0</swingHeight>
      </us.ihmc.humanoidRobotics.communication.packets.walking.FootstepDataMessage>
    </footstepDataList>
    <swingTime>0.0</swingTime>
    <transferTime>0.0</transferTime>
  </us.ihmc.humanoidRobotics.communication.packets.walking.FootstepDataListMessage>
  <long>1457583856328</long>
  <us.ihmc.humanoidRobotics.communication.packets.walking.PauseWalkingMessage>
    <uniqueId>-1</uniqueId>
    <destination>0</destination>
    <pause>true</pause>
  </us.ihmc.humanoidRobotics.communication.packets.walking.PauseWalkingMessage>
  <long>1457583856328</long>
  <us.ihmc.humanoidRobotics.communication.packets.walking.EndOfScriptCommand>
    <uniqueId>0</uniqueId>
    <destination>0</destination>
  </us.ihmc.humanoidRobotics.communication.packets.walking.EndOfScriptCommand>
</object-stream>