{
  "name" : "door",
  "object" : "PullDoorLeverHandle",
  "x" : 0.0,
  "y" : 0.0,
  "z" : 0.0,
  "m00" : 1.0,
  "m01" : 0.0,
  "m02" : 0.0,
  "m10" : 0.0,
  "m11" : -1.0,
  "m12" : -1.2246467991473532E-16,
  "m20" : 0.0,
  "m21" : 1.2246467991473532E-16,
  "m22" : -1.0,
  "frames" : [ {
    "x" : 0.0,
    "y" : 0.0,
    "z" : 0.0,
    "m00" : 1.0,
    "m01" : 0.0,
    "m02" : 0.0,
    "m10" : 0.0,
    "m11" : -1.0,
    "m12" : -1.2246467991473532E-16,
    "m20" : 0.0,
    "m21" : 1.2246467991473532E-16,
    "m22" : -1.0
  }, {
    "x" : 0.0,
    "y" : 0.0,
    "z" : 0.0,
    "m00" : 1.0,
    "m01" : 0.0,
    "m02" : 0.0,
    "m10" : 0.0,
    "m11" : -1.0,
    "m12" : -1.2246467991473532E-16,
    "m20" : 0.0,
    "m21" : 1.2246467991473532E-16,
    "m22" : -1.0
  }, {
    "x" : 0.0,
    "y" : 0.0,
    "z" : 0.0,
    "m00" : 1.0,
    "m01" : 0.0,
    "m02" : 0.0,
    "m10" : 0.0,
    "m11" : -1.0,
    "m12" : -1.2246467991473532E-16,
    "m20" : 0.0,
    "m21" : 1.2246467991473532E-16,
    "m22" : -1.0
  }, {
    "x" : 0.0,
    "y" : 0.0,
    "z" : 0.0,
    "m00" : 1.0,
    "m01" : 0.0,
    "m02" : 0.0,
    "m10" : 0.0,
    "m11" : -1.0,
    "m12" : -1.2246467991473532E-16,
    "m20" : 0.0,
    "m21" : 1.2246467991473532E-16,
    "m22" : -1.0
  } ],
  "#preGraspFrames" : 1,
  "#postGraspFrames" : 2
}