<object-stream>
  <long>0</long>
  <us.ihmc.humanoidRobotics.communication.packets.walking.FootstepDataListMessage>
    <uniqueId>-1</uniqueId>
    <destination>0</destination>
    <source>0</source>
    <footstepDataList>
      <clazz>us.ihmc.humanoidRobotics.communication.packets.walking.FootstepDataMessage</clazz>
      <values class="us.ihmc.humanoidRobotics.communication.packets.walking.FootstepDataMessage-array">
        <us.ihmc.humanoidRobotics.communication.packets.walking.FootstepDataMessage>
          <uniqueId>0</uniqueId>
          <destination>0</destination>
          <source>0</source>
          <robotSide>1</robotSide>
          <location>
            <x>0.5256588991888308</x>
            <y>-0.168015789765116</y>
            <z>0.0034022527812858916</z>
          </location>
          <orientation>
            <x>2.152526913793795E-4</x>
            <y>-0.0039267323895573955</y>
            <z>-0.0010246821224833887</z>
            <s>0.9999917421986881</s>
          </orientation>
          <predictedContactPoints>
            <clazz>us.ihmc.euclid.tuple2D.Point2D</clazz>
            <values class="us.ihmc.euclid.tuple2D.Point2D-array"/>
            <pos>-1</pos>
            <isEnum>false</isEnum>
          </predictedContactPoints>
          <trajectoryType>0</trajectoryType>
          <swingHeight>0.0</swingHeight>
          <positionWaypoints>
            <clazz>us.ihmc.euclid.tuple3D.Point3D</clazz>
            <values class="us.ihmc.euclid.tuple3D.Point3D-array"/>
            <pos>-1</pos>
            <isEnum>false</isEnum>
          </positionWaypoints>
          <swingTrajectory>
            <clazz>us.ihmc.humanoidRobotics.communication.packets.SE3TrajectoryPointMessage</clazz>
            <values class="us.ihmc.humanoidRobotics.communication.packets.SE3TrajectoryPointMessage-array"/>
            <pos>-1</pos>
            <isEnum>false</isEnum>
          </swingTrajectory>
          <swingTrajectoryBlendDuration>0.0</swingTrajectoryBlendDuration>
          <swingDuration>-1.0</swingDuration>
          <transferDuration>-1.0</transferDuration>
          <touchdownDuration>-1.0</touchdownDuration>
          <executionDelayTime>0.0</executionDelayTime>
        </us.ihmc.humanoidRobotics.communication.packets.walking.FootstepDataMessage>
        <us.ihmc.humanoidRobotics.communication.packets.walking.FootstepDataMessage>
          <uniqueId>0</uniqueId>
          <destination>0</destination>
          <source>0</source>
          <robotSide>0</robotSide>
          <location>
            <x>1.0256588991888307</x>
            <y>0.081984210234884</y>
            <z>0.006109460888215734</z>
          </location>
          <orientation>
            <x>2.152526913793793E-4</x>
            <y>-0.003926732389557397</y>
            <z>-0.0010246821224833887</z>
            <s>0.9999917421986881</s>
          </orientation>
          <predictedContactPoints>
            <clazz>us.ihmc.euclid.tuple2D.Point2D</clazz>
            <values class="us.ihmc.euclid.tuple2D.Point2D-array"/>
            <pos>-1</pos>
            <isEnum>false</isEnum>
          </predictedContactPoints>
          <trajectoryType>0</trajectoryType>
          <swingHeight>0.0</swingHeight>
          <positionWaypoints>
            <clazz>us.ihmc.euclid.tuple3D.Point3D</clazz>
            <values class="us.ihmc.euclid.tuple3D.Point3D-array"/>
            <pos>-1</pos>
            <isEnum>false</isEnum>
          </positionWaypoints>
          <swingTrajectory>
            <clazz>us.ihmc.humanoidRobotics.communication.packets.SE3TrajectoryPointMessage</clazz>
            <values class="us.ihmc.humanoidRobotics.communication.packets.SE3TrajectoryPointMessage-array"/>
            <pos>-1</pos>
            <isEnum>false</isEnum>
          </swingTrajectory>
          <swingTrajectoryBlendDuration>0.0</swingTrajectoryBlendDuration>
          <swingDuration>-1.0</swingDuration>
          <transferDuration>-1.0</transferDuration>
          <touchdownDuration>-1.0</touchdownDuration>
          <executionDelayTime>0.0</executionDelayTime>
        </us.ihmc.humanoidRobotics.communication.packets.walking.FootstepDataMessage>
        <us.ihmc.humanoidRobotics.communication.packets.walking.FootstepDataMessage>
          <uniqueId>0</uniqueId>
          <destination>0</destination>
          <source>0</source>
          <robotSide>1</robotSide>
          <location>
            <x>1.5256588991888307</x>
            <y>-0.168015789765116</y>
            <z>0.008597240204584244</z>
          </location>
          <orientation>
            <x>2.1525269137937961E-4</x>
            <y>-0.003926732389557397</y>
            <z>-0.0010246821224833887</z>
            <s>0.9999917421986881</s>
          </orientation>
          <predictedContactPoints>
            <clazz>us.ihmc.euclid.tuple2D.Point2D</clazz>
            <values class="us.ihmc.euclid.tuple2D.Point2D-array"/>
            <pos>-1</pos>
            <isEnum>false</isEnum>
          </predictedContactPoints>
          <trajectoryType>0</trajectoryType>
          <swingHeight>0.0</swingHeight>
          <positionWaypoints>
            <clazz>us.ihmc.euclid.tuple3D.Point3D</clazz>
            <values class="us.ihmc.euclid.tuple3D.Point3D-array"/>
            <pos>-1</pos>
            <isEnum>false</isEnum>
          </positionWaypoints>
          <swingTrajectory>
            <clazz>us.ihmc.humanoidRobotics.communication.packets.SE3TrajectoryPointMessage</clazz>
            <values class="us.ihmc.humanoidRobotics.communication.packets.SE3TrajectoryPointMessage-array"/>
            <pos>-1</pos>
            <isEnum>false</isEnum>
          </swingTrajectory>
          <swingTrajectoryBlendDuration>0.0</swingTrajectoryBlendDuration>
          <swingDuration>-1.0</swingDuration>
          <transferDuration>-1.0</transferDuration>
          <touchdownDuration>-1.0</touchdownDuration>
          <executionDelayTime>0.0</executionDelayTime>
        </us.ihmc.humanoidRobotics.communication.packets.walking.FootstepDataMessage>
        <us.ihmc.humanoidRobotics.communication.packets.walking.FootstepDataMessage>
          <uniqueId>0</uniqueId>
          <destination>0</destination>
          <source>0</source>
          <robotSide>0</robotSide>
          <location>
            <x>2.025658899188831</x>
            <y>0.081984210234884</y>
            <z>0.011304294087297481</z>
          </location>
          <orientation>
            <x>2.1525269137938043E-4</x>
            <y>-0.003926732389557397</y>
            <z>-0.0010246821224833887</z>
            <s>0.9999917421986881</s>
          </orientation>
          <predictedContactPoints>
            <clazz>us.ihmc.euclid.tuple2D.Point2D</clazz>
            <values class="us.ihmc.euclid.tuple2D.Point2D-array"/>
            <pos>-1</pos>
            <isEnum>false</isEnum>
          </predictedContactPoints>
          <trajectoryType>0</trajectoryType>
          <swingHeight>0.0</swingHeight>
          <positionWaypoints>
            <clazz>us.ihmc.euclid.tuple3D.Point3D</clazz>
            <values class="us.ihmc.euclid.tuple3D.Point3D-array"/>
            <pos>-1</pos>
            <isEnum>false</isEnum>
          </positionWaypoints>
          <swingTrajectory>
            <clazz>us.ihmc.humanoidRobotics.communication.packets.SE3TrajectoryPointMessage</clazz>
            <values class="us.ihmc.humanoidRobotics.communication.packets.SE3TrajectoryPointMessage-array"/>
            <pos>-1</pos>
            <isEnum>false</isEnum>
          </swingTrajectory>
          <swingTrajectoryBlendDuration>0.0</swingTrajectoryBlendDuration>
          <swingDuration>-1.0</swingDuration>
          <transferDuration>-1.0</transferDuration>
          <touchdownDuration>-1.0</touchdownDuration>
          <executionDelayTime>0.0</executionDelayTime>
        </us.ihmc.humanoidRobotics.communication.packets.walking.FootstepDataMessage>
        <us.ihmc.humanoidRobotics.communication.packets.walking.FootstepDataMessage>
          <uniqueId>0</uniqueId>
          <destination>0</destination>
          <source>0</source>
          <robotSide>1</robotSide>
          <location>
            <x>2.525658899188831</x>
            <y>-0.168015789765116</y>
            <z>0.013792073403665991</z>
          </location>
          <orientation>
            <x>2.1525269137937961E-4</x>
            <y>-0.003926732389557397</y>
            <z>-0.0010246821224833887</z>
            <s>0.9999917421986881</s>
          </orientation>
          <predictedContactPoints>
            <clazz>us.ihmc.euclid.tuple2D.Point2D</clazz>
            <values class="us.ihmc.euclid.tuple2D.Point2D-array"/>
            <pos>-1</pos>
            <isEnum>false</isEnum>
          </predictedContactPoints>
          <trajectoryType>0</trajectoryType>
          <swingHeight>0.0</swingHeight>
          <positionWaypoints>
            <clazz>us.ihmc.euclid.tuple3D.Point3D</clazz>
            <values class="us.ihmc.euclid.tuple3D.Point3D-array"/>
            <pos>-1</pos>
            <isEnum>false</isEnum>
          </positionWaypoints>
          <swingTrajectory>
            <clazz>us.ihmc.humanoidRobotics.communication.packets.SE3TrajectoryPointMessage</clazz>
            <values class="us.ihmc.humanoidRobotics.communication.packets.SE3TrajectoryPointMessage-array"/>
            <pos>-1</pos>
            <isEnum>false</isEnum>
          </swingTrajectory>
          <swingTrajectoryBlendDuration>0.0</swingTrajectoryBlendDuration>
          <swingDuration>-1.0</swingDuration>
          <transferDuration>-1.0</transferDuration>
          <touchdownDuration>-1.0</touchdownDuration>
          <executionDelayTime>0.0</executionDelayTime>
        </us.ihmc.humanoidRobotics.communication.packets.walking.FootstepDataMessage>
        <us.ihmc.humanoidRobotics.communication.packets.walking.FootstepDataMessage>
          <uniqueId>0</uniqueId>
          <destination>0</destination>
          <source>0</source>
          <robotSide>0</robotSide>
          <location>
            <x>3.025658899188831</x>
            <y>0.081984210234884</y>
            <z>0.013901710686838348</z>
          </location>
          <orientation>
            <x>2.1525269137938037E-4</x>
            <y>-0.003926732389557397</y>
            <z>-0.0010246821224833887</z>
            <s>0.9999917421986881</s>
          </orientation>
          <predictedContactPoints>
            <clazz>us.ihmc.euclid.tuple2D.Point2D</clazz>
            <values class="us.ihmc.euclid.tuple2D.Point2D-array"/>
            <pos>-1</pos>
            <isEnum>false</isEnum>
          </predictedContactPoints>
          <trajectoryType>0</trajectoryType>
          <swingHeight>0.0</swingHeight>
          <positionWaypoints>
            <clazz>us.ihmc.euclid.tuple3D.Point3D</clazz>
            <values class="us.ihmc.euclid.tuple3D.Point3D-array"/>
            <pos>-1</pos>
            <isEnum>false</isEnum>
          </positionWaypoints>
          <swingTrajectory>
            <clazz>us.ihmc.humanoidRobotics.communication.packets.SE3TrajectoryPointMessage</clazz>
            <values class="us.ihmc.humanoidRobotics.communication.packets.SE3TrajectoryPointMessage-array"/>
            <pos>-1</pos>
            <isEnum>false</isEnum>
          </swingTrajectory>
          <swingTrajectoryBlendDuration>0.0</swingTrajectoryBlendDuration>
          <swingDuration>-1.0</swingDuration>
          <transferDuration>-1.0</transferDuration>
          <touchdownDuration>-1.0</touchdownDuration>
          <executionDelayTime>0.0</executionDelayTime>
        </us.ihmc.humanoidRobotics.communication.packets.walking.FootstepDataMessage>
        <us.ihmc.humanoidRobotics.communication.packets.walking.FootstepDataMessage>
          <uniqueId>0</uniqueId>
          <destination>0</destination>
          <source>0</source>
          <robotSide>1</robotSide>
          <location>
            <x>3.025658899188831</x>
            <y>-0.168015789765116</y>
            <z>0.013901710686838348</z>
          </location>
          <orientation>
            <x>2.1525269137938037E-4</x>
            <y>-0.003926732389557397</y>
            <z>-0.0010246821224833887</z>
            <s>0.9999917421986881</s>
          </orientation>
          <predictedContactPoints>
            <clazz>us.ihmc.euclid.tuple2D.Point2D</clazz>
            <values class="us.ihmc.euclid.tuple2D.Point2D-array"/>
            <pos>-1</pos>
            <isEnum>false</isEnum>
          </predictedContactPoints>
          <trajectoryType>0</trajectoryType>
          <swingHeight>0.0</swingHeight>
          <positionWaypoints>
            <clazz>us.ihmc.euclid.tuple3D.Point3D</clazz>
            <values class="us.ihmc.euclid.tuple3D.Point3D-array"/>
            <pos>-1</pos>
            <isEnum>false</isEnum>
          </positionWaypoints>
          <swingTrajectory>
            <clazz>us.ihmc.humanoidRobotics.communication.packets.SE3TrajectoryPointMessage</clazz>
            <values class="us.ihmc.humanoidRobotics.communication.packets.SE3TrajectoryPointMessage-array"/>
            <pos>-1</pos>
            <isEnum>false</isEnum>
          </swingTrajectory>
          <swingTrajectoryBlendDuration>0.0</swingTrajectoryBlendDuration>
          <swingDuration>-1.0</swingDuration>
          <transferDuration>-1.0</transferDuration>
          <touchdownDuration>-1.0</touchdownDuration>
          <executionDelayTime>0.0</executionDelayTime>
        </us.ihmc.humanoidRobotics.communication.packets.walking.FootstepDataMessage>
      </values>
      <pos>6</pos>
      <isEnum>false</isEnum>
    </footstepDataList>
    <executionTiming>0</executionTiming>
    <defaultSwingDuration>0.75</defaultSwingDuration>
    <defaultTransferDuration>0.15</defaultTransferDuration>
    <finalTransferDuration>0.15</finalTransferDuration>
    <trustHeightOfFootsteps>true</trustHeightOfFootsteps>
    <areFootstepsAdjustable>false</areFootstepsAdjustable>
    <offsetFootstepsWithExecutionError>false</offsetFootstepsWithExecutionError>
    <queueingProperties>
      <uniqueId>0</uniqueId>
      <destination>0</destination>
      <source>0</source>
      <executionMode>0</executionMode>
      <previousMessageId>0</previousMessageId>
      <executionDelayTime>0.0</executionDelayTime>
    </queueingProperties>
  </us.ihmc.humanoidRobotics.communication.packets.walking.FootstepDataListMessage>
  <long>0</long>
  <us.ihmc.humanoidRobotics.communication.packets.walking.EndOfScriptCommand>
    <uniqueId>0</uniqueId>
    <destination>0</destination>
    <source>0</source>
  </us.ihmc.humanoidRobotics.communication.packets.walking.EndOfScriptCommand>
</object-stream>