<package>
  <description brief="collider - collision avoidance for tabletop manipulation using octomap">

    collider - collision avoidance for tabletop manipulation using octomap

  </description>
  <author>Adam Harmat, Gil E. Jones, Kai M. Wurm, Armin Hornung. Maintained by Gil E. Jones</author>
  <license>BSD</license>
  <review status="unreviewed" notes=""/>
  
  <depend package="roscpp"/>
  <depend package="tf"/>
  <depend package="visualization_msgs"/>
  <depend package="arm_navigation_msgs"/>
  <depend package="std_msgs"/>
  <depend package="std_srvs"/>
  <depend package="actionlib"/>
  <depend package="actionlib_msgs"/>
  <depend package="pcl"/>
  <depend package="pcl_ros"/>
  <depend package="image_transport"/>
  <depend package="image_geometry"/>
  <depend package="robot_self_filter"/>
  <depend package="planning_environment"/>
  <depend package="common_rosdeps"/>

  <rosdep name="eigen" />
  <rosdep name="opencv2" />

</package>


