{
  "environment" : [ {
    "ihmc_common_msgs::msg::dds_::Box3DMessage_" : {
      "size" : {
        "x" : 10.0,
        "y" : 10.0,
        "z" : 1.0
      },
      "pose" : {
        "position" : {
          "x" : 0.0,
          "y" : 0.0,
          "z" : -0.5
        },
        "orientation" : {
          "x" : 0.0,
          "y" : 0.0,
          "z" : 0.0,
          "w" : 1.0
        }
      }
    }
  }, {
    "ihmc_common_msgs::msg::dds_::Box3DMessage_" : {
      "size" : {
        "x" : 0.2,
        "y" : 0.8,
        "z" : 2.0
      },
      "pose" : {
        "position" : {
          "x" : 0.7,
          "y" : 0.0,
          "z" : 1.0
        },
        "orientation" : {
          "x" : 0.0,
          "y" : 0.0,
          "z" : 0.0,
          "w" : 1.0
        }
      }
    }
  } ],
  "script" : [ {
    "KinematicsToolboxSnapshotDescription" : {
      "controllerConfiguration" : {
        "controller_msgs::msg::dds_::RobotConfigurationData_" : {
          "sequence_id" : 4057,
          "wall_time" : 1698248681286,
          "monotonic_time" : 1698248681286,
          "sync_timestamp" : 0,
          "joint_name_hash" : -1361652808,
          "joint_angles" : [ 0.03283238, 0.005456812, -0.482644, 0.72963655, -0.58879405, -0.14459953, -0.10281367, -0.09319206, -0.29619363, 0.8202252, -0.81035566, -0.06254968, 0.35746935, 0.0062618856, 0.015471647, -0.08545569, -1.1117655, -0.113245115, -1.7722967, 0.009003933, -0.0026125542, -0.0036626947, 7.092416, -0.0425171, 1.1773391, 1.0803583, 1.6957788 ],
          "joint_velocities" : [ ],
          "joint_torques" : [ 16.067135, 61.54733, 8.018545, 12.592595, -0.8731063, 1.0424502, 83.67767, -185.1112, -6.1178474, -160.20198, 24.139595, 42.893654, -101.21633, -47.96186, 14.757801, -106.610115, 26.61932, -13.975732, -65.0, 1.8575603, 0.5014458, -2.8118944, 0.0, -52.385475, -42.243996, -65.0, 2.0680122 ],
          "root_position" : {
            "x" : 0.402617227890587,
            "y" : -0.5797100561537484,
            "z" : 0.9574267343462441
          },
          "root_orientation" : {
            "x" : 0.3390367924674752,
            "y" : 0.1504318474790913,
            "z" : 0.1720106116272014,
            "w" : 0.9125988505937564
          },
          "pelvis_linear_velocity" : {
            "x" : 0.2654598217265878,
            "y" : -0.8816154651430864,
            "z" : 0.19980687073927775
          },
          "pelvis_angular_velocity" : {
            "x" : 0.9255372200622916,
            "y" : 0.6310140510583978,
            "z" : 1.6874275634646305
          },
          "pelvis_linear_acceleration" : {
            "x" : -3.776660282180379,
            "y" : -6.6680411335532925,
            "z" : -4.5841301275525606
          },
          "force_sensor_data" : [ ],
          "imu_sensor_data" : [ ],
          "robot_motion_status" : 0,
          "last_received_packet_type_id" : -1,
          "last_received_packet_unique_id" : -1,
          "last_received_packet_robot_timestamp" : -1
        }
      },
      "ikSolution" : {
        "toolbox_msgs::msg::dds_::KinematicsToolboxOutputStatus_" : {
          "sequence_id" : 0,
          "current_toolbox_state" : 3,
          "joint_name_hash" : 1976133317,
          "desired_joint_angles" : [ 0.034999214, 0.011310542, -0.48182827, 0.73126084, -0.5889922, -0.1442327, -0.09354217, -0.11059301, -0.29681623, 0.800352, -0.8012119, -0.03903912, 0.3495281, 0.004588451, 0.015760861, -0.098483615, -1.108097, -0.115145154, -1.8265964, 0.010706022, -0.0019438491, -0.0056451536, 0.0026477047, -0.04910834, 1.1719378, 0.54246175, 1.696206 ],
          "desired_root_position" : {
            "x" : 0.1750671703958233,
            "y" : -0.2131450026004101,
            "z" : 1.0447053033101814
          },
          "desired_root_orientation" : {
            "x" : 0.09952925183124016,
            "y" : 0.13905100708325396,
            "z" : -0.0738330661399694,
            "w" : 0.9825005973552472
          },
          "desired_joint_velocities" : [ -2.0351776E-11, 5.926856E-11, 4.390932E-11, 2.2093438E-11, -1.5099033E-11, 3.658185E-11, -1.1241008E-11, 5.201395E-11, 1.2123635E-10, -1.2767565E-10, 6.783463E-11, 3.5915715E-11, 8.926193E-11, 1.7606576E-11, -4.4519943E-11, -1.4376E-10, -5.107026E-12, 2.3750446E-10, -1.01918474E-10, 5.4158067E-12, 8.8099014E-11, -2.1640675E-12, 2.9504747E-5, 1.4958867E-10, -9.969803E-11, -1.4477308E-10, 1.7763568E-11 ],
          "desired_root_linear_velocity" : {
            "x" : -1.0994768330040064E-11,
            "y" : 4.6830585063399675E-11,
            "z" : 7.980837485553155E-12
          },
          "desired_root_angular_velocity" : {
            "x" : -9.194900819647389E-11,
            "y" : -5.4398795802641547E-11,
            "z" : 7.66718097576591E-12
          },
          "support_region" : [ {
            "x" : -0.04702511811860421,
            "y" : -0.25052609199210546,
            "z" : 0.0
          }, {
            "x" : 0.05992810716615102,
            "y" : 0.15708424492739803,
            "z" : 0.0
          }, {
            "x" : 0.243609350115156,
            "y" : 0.23527711279978336,
            "z" : 0.0
          }, {
            "x" : 0.5237706587647248,
            "y" : 0.2761213023612838,
            "z" : 0.0
          }, {
            "x" : 0.5872769412794517,
            "y" : 0.27512964544134993,
            "z" : 0.0
          }, {
            "x" : 0.6434471612005433,
            "y" : 0.24496809339121256,
            "z" : 0.0
          }, {
            "x" : 0.65922868331709,
            "y" : 0.2311024208303339,
            "z" : 0.0
          }, {
            "x" : 0.7035199725376862,
            "y" : 0.16528194619083944,
            "z" : 0.0
          }, {
            "x" : 0.7359071816164016,
            "y" : -0.061858182666645084,
            "z" : 0.0
          }, {
            "x" : 0.7356120644561794,
            "y" : -0.06283340204621682,
            "z" : 0.0
          }, {
            "x" : 0.641655744203189,
            "y" : -0.14430830298934227,
            "z" : 0.0
          }, {
            "x" : 0.5442234628593279,
            "y" : -0.19436747922135705,
            "z" : 0.0
          }, {
            "x" : 0.1675069656588583,
            "y" : -0.27240257350338226,
            "z" : 0.0
          }, {
            "x" : -0.033076034452601454,
            "y" : -0.2611825165466675,
            "z" : 0.0
          }, {
            "x" : -0.03986304835473753,
            "y" : -0.2574027680345775,
            "z" : 0.0
          } ],
          "solution_quality" : 3.611071870743754E-4
        }
      },
      "ikPrivilegedConfiguration" : {
        "toolbox_msgs::msg::dds_::KinematicsToolboxPrivilegedConfigurationMessage_" : {
          "sequence_id" : 0,
          "use_privileged_root_joint_position" : false,
          "use_privileged_root_joint_orientation" : false,
          "privileged_root_joint_position" : {
            "x" : 0.0,
            "y" : 0.0,
            "z" : 0.0
          },
          "privileged_root_joint_orientation" : {
            "x" : 0.0,
            "y" : 0.0,
            "z" : 0.0,
            "w" : 1.0
          },
          "privileged_joint_hash_codes" : [ ],
          "privileged_joint_angles" : [ ],
          "privileged_weight" : 0.5,
          "privileged_gain" : 100.0
        }
      },
      "centerOfMassAnchor" : {
        "CenterOfMassMotionControlAnchorDescription" : {
          "isTrackingController" : false,
          "ikSolverMessage" : {
            "toolbox_msgs::msg::dds_::KinematicsToolboxCenterOfMassMessage_" : {
              "sequence_id" : 0,
              "desired_position_in_world" : {
                "x" : 0.18829548763605652,
                "y" : -0.2043333481545995,
                "z" : 0.9769428706449123
              },
              "selection_matrix" : {
                "sequence_id" : 0,
                "selection_frame_id" : 83766130,
                "x_selected" : true,
                "y_selected" : true,
                "z_selected" : true
              },
              "weights" : {
                "sequence_id" : 0,
                "weight_frame_id" : 0,
                "x_weight" : 7.77075798929424E-5,
                "y_weight" : 7.77075798929424E-5,
                "z_weight" : 7.77075798929424E-5
              }
            }
          }
        }
      },
      "sixDoFAnchors" : [ {
        "SixDoFMotionControlAnchorDescription" : {
          "rigidBodyName" : "leftFoot",
          "isContactState" : true,
          "isTrackingController" : false,
          "anchorId" : 16,
          "contactNormalInWorld" : "4.2887037357565883E-4,7.700786001484398E-5,0.9999999050699917",
          "ikSolverMessage" : {
            "toolbox_msgs::msg::dds_::KinematicsToolboxRigidBodyMessage_" : {
              "sequence_id" : 0,
              "end_effector_hash_code" : 532235394,
              "desired_position_in_world" : {
                "x" : 0.05992810716615414,
                "y" : 0.15708424492742934,
                "z" : -9.238935278103183E-4
              },
              "desired_orientation_in_world" : {
                "x" : 0.022139036341168296,
                "y" : -0.027730546260930553,
                "z" : 0.012666879143350844,
                "w" : 0.999289962947053
              },
              "control_frame_position_in_end_effector" : {
                "x" : -0.015254304515944388,
                "y" : 0.010887763052793722,
                "z" : -0.04107207585965925
              },
              "control_frame_orientation_in_end_effector" : {
                "x" : 3.3881317890172014E-21,
                "y" : 5.929230630780102E-21,
                "z" : 0.089471128262573,
                "w" : 0.9959894162125533
              },
              "angular_selection_matrix" : {
                "sequence_id" : 0,
                "selection_frame_id" : 0,
                "x_selected" : true,
                "y_selected" : true,
                "z_selected" : true
              },
              "linear_selection_matrix" : {
                "sequence_id" : 0,
                "selection_frame_id" : 83766130,
                "x_selected" : true,
                "y_selected" : true,
                "z_selected" : true
              },
              "angular_weight_matrix" : {
                "sequence_id" : 0,
                "weight_frame_id" : 0,
                "x_weight" : 200.0,
                "y_weight" : 200.0,
                "z_weight" : 200.0
              },
              "linear_weight_matrix" : {
                "sequence_id" : 0,
                "weight_frame_id" : 0,
                "x_weight" : 200.0,
                "y_weight" : 200.0,
                "z_weight" : 200.0
              }
            }
          }
        }
      }, {
        "SixDoFMotionControlAnchorDescription" : {
          "rigidBodyName" : "rightElbowPitchLink",
          "isContactState" : true,
          "isTrackingController" : false,
          "anchorId" : 13,
          "contactNormalInWorld" : "-0.9954681755813669,0.0717846362786771,-0.06237048499926323",
          "ikSolverMessage" : {
            "toolbox_msgs::msg::dds_::KinematicsToolboxRigidBodyMessage_" : {
              "sequence_id" : 0,
              "end_effector_hash_code" : 601127246,
              "desired_position_in_world" : {
                "x" : 0.584978045184384,
                "y" : -0.2954747192716598,
                "z" : 0.8887877774279301
              },
              "desired_orientation_in_world" : {
                "x" : 0.17584203562966164,
                "y" : -0.6925924245556717,
                "z" : 0.08549469418036838,
                "w" : 0.6943241096352036
              },
              "control_frame_position_in_end_effector" : {
                "x" : -0.013808607450518429,
                "y" : -0.26958831282462187,
                "z" : 0.007164019633453455
              },
              "control_frame_orientation_in_end_effector" : {
                "x" : -0.8276429250197879,
                "y" : -0.09289280844352957,
                "z" : -0.007927123395434554,
                "w" : 0.553457564334283
              },
              "angular_selection_matrix" : {
                "sequence_id" : 0,
                "selection_frame_id" : 0,
                "x_selected" : false,
                "y_selected" : false,
                "z_selected" : false
              },
              "linear_selection_matrix" : {
                "sequence_id" : 0,
                "selection_frame_id" : 83766130,
                "x_selected" : true,
                "y_selected" : true,
                "z_selected" : true
              },
              "angular_weight_matrix" : {
                "sequence_id" : 0,
                "weight_frame_id" : 0,
                "x_weight" : 200.0,
                "y_weight" : 200.0,
                "z_weight" : 200.0
              },
              "linear_weight_matrix" : {
                "sequence_id" : 0,
                "weight_frame_id" : 0,
                "x_weight" : 200.0,
                "y_weight" : 200.0,
                "z_weight" : 200.0
              }
            }
          }
        }
      }, {
        "SixDoFMotionControlAnchorDescription" : {
          "rigidBodyName" : "rightFoot",
          "isContactState" : true,
          "isTrackingController" : false,
          "anchorId" : 15,
          "contactNormalInWorld" : "6.600420559459451E-4,-9.495861906611605E-5,0.9999997776636478",
          "ikSolverMessage" : {
            "toolbox_msgs::msg::dds_::KinematicsToolboxRigidBodyMessage_" : {
              "sequence_id" : 0,
              "end_effector_hash_code" : -284345206,
              "desired_position_in_world" : {
                "x" : -0.04967764451433811,
                "y" : -0.2606351576605308,
                "z" : -0.0013903530421537705
              },
              "desired_orientation_in_world" : {
                "x" : 0.002930334074958567,
                "y" : 0.004684186544563495,
                "z" : -5.079411601817737E-5,
                "w" : 0.9999847343627714
              },
              "control_frame_position_in_end_effector" : {
                "x" : 0.12141803941395089,
                "y" : -0.02779126485793054,
                "z" : -0.04107207585965924
              },
              "control_frame_orientation_in_end_effector" : {
                "x" : 6.776263578034403E-21,
                "y" : 1.6940658945086007E-21,
                "z" : 0.11595647302333911,
                "w" : 0.9932542959202278
              },
              "angular_selection_matrix" : {
                "sequence_id" : 0,
                "selection_frame_id" : 0,
                "x_selected" : true,
                "y_selected" : true,
                "z_selected" : true
              },
              "linear_selection_matrix" : {
                "sequence_id" : 0,
                "selection_frame_id" : 83766130,
                "x_selected" : true,
                "y_selected" : true,
                "z_selected" : true
              },
              "angular_weight_matrix" : {
                "sequence_id" : 0,
                "weight_frame_id" : 0,
                "x_weight" : 200.0,
                "y_weight" : 200.0,
                "z_weight" : 200.0
              },
              "linear_weight_matrix" : {
                "sequence_id" : 0,
                "weight_frame_id" : 0,
                "x_weight" : 200.0,
                "y_weight" : 200.0,
                "z_weight" : 200.0
              }
            }
          }
        }
      }, {
        "SixDoFMotionControlAnchorDescription" : {
          "rigidBodyName" : "leftElbowPitchLink",
          "isContactState" : true,
          "isTrackingController" : false,
          "anchorId" : 14,
          "contactNormalInWorld" : "-0.9974736879054011,0.002618628710119912,-0.07098862387789646",
          "ikSolverMessage" : {
            "toolbox_msgs::msg::dds_::KinematicsToolboxRigidBodyMessage_" : {
              "sequence_id" : 0,
              "end_effector_hash_code" : 612165328,
              "desired_position_in_world" : {
                "x" : 0.5751717949385453,
                "y" : 0.2558836340422632,
                "z" : 1.1832002321597712
              },
              "desired_orientation_in_world" : {
                "x" : 0.21459431144873398,
                "y" : -0.6046392273012502,
                "z" : 0.023067291963346483,
                "w" : 0.766699801971977
              },
              "control_frame_position_in_end_effector" : {
                "x" : -0.04753517691892439,
                "y" : 0.2695095866740529,
                "z" : -0.02168349788676061
              },
              "control_frame_orientation_in_end_effector" : {
                "x" : 0.6960226067255739,
                "y" : -0.013331472162653752,
                "z" : 0.29946994951549943,
                "w" : 0.6524511875336712
              },
              "angular_selection_matrix" : {
                "sequence_id" : 0,
                "selection_frame_id" : 0,
                "x_selected" : false,
                "y_selected" : false,
                "z_selected" : false
              },
              "linear_selection_matrix" : {
                "sequence_id" : 0,
                "selection_frame_id" : 83766130,
                "x_selected" : true,
                "y_selected" : true,
                "z_selected" : true
              },
              "angular_weight_matrix" : {
                "sequence_id" : 0,
                "weight_frame_id" : 0,
                "x_weight" : 200.0,
                "y_weight" : 200.0,
                "z_weight" : 200.0
              },
              "linear_weight_matrix" : {
                "sequence_id" : 0,
                "weight_frame_id" : 0,
                "x_weight" : 200.0,
                "y_weight" : 200.0,
                "z_weight" : 200.0
              }
            }
          }
        }
      } ],
      "oneDoFAnchors" : [ ],
      "executionDuration" : "NaN"
    }
  } ]
}